elastichash/__init__.py
elastichash/elastichash.py
elastichash/templates.py
elastichash/util.py
elastichash-0.1.5.dist-info/LICENSE
elastichash-0.1.5.dist-info/METADATA
elastichash-0.1.5.dist-info/WHEEL
elastichash-0.1.5.dist-info/top_level.txt
elastichash-0.1.5.dist-info/RECORD
