Metadata-Version: 2.1
Name: elastichash
Version: 0.1.5
Summary: ElasticHash enables efficient similarity search for binary hash codes using Elasticsearch
Home-page: https://nik-ko.github.io/elastichash/
Author: Nikolaus Korfhage
Author-email: nko+py@posteo.ru
License: MIT
Project-URL: Source, https://github.com/nik-ko/elastichash
Project-URL: Bug Tracker, https://github.com/nik-ko/elastichash/issues
Project-URL: Documentation, https://nik-ko.github.io/elastichash/
Classifier: Programming Language :: Python :: 3
Classifier: License :: OSI Approved :: MIT License
Classifier: Operating System :: OS Independent
Requires-Python: >=3.7
License-File: LICENSE
Requires-Dist: elasticsearch >=8.10.1
Requires-Dist: numpy >=1.24.3
Requires-Dist: networkx >=3.1
Requires-Dist: bitstring >=4.1.1
Requires-Dist: urllib3 >=1.26.16
Requires-Dist: matplotlib >=3.7.1
Requires-Dist: seaborn >=0.12.2
